odoo/addons/purchase_report_date_format/README.rst
odoo/addons/purchase_report_date_format/__init__.py
odoo/addons/purchase_report_date_format/__manifest__.py
odoo/addons/purchase_report_date_format/i18n/it.po
odoo/addons/purchase_report_date_format/i18n/pt_BR.po
odoo/addons/purchase_report_date_format/i18n/purchase_report_date_format.pot
odoo/addons/purchase_report_date_format/readme/CONTRIBUTORS.md
odoo/addons/purchase_report_date_format/readme/DESCRIPTION.md
odoo/addons/purchase_report_date_format/reports/purchase_quotation_templates.xml
odoo/addons/purchase_report_date_format/static/description/icon.png
odoo/addons/purchase_report_date_format/static/description/index.html
odoo_addon_purchase_report_date_format-18.0.1.0.0.2.dist-info/METADATA
odoo_addon_purchase_report_date_format-18.0.1.0.0.2.dist-info/WHEEL
odoo_addon_purchase_report_date_format-18.0.1.0.0.2.dist-info/top_level.txt
odoo_addon_purchase_report_date_format-18.0.1.0.0.2.dist-info/RECORD
