Metadata-Version: 2.1
Name: odoo-addon-purchase_report_date_format
Version: 18.0.1.0.0.2
Requires-Python: >=3.10
Requires-Dist: odoo==18.0.*
Summary: Purchase Report Date Format
Home-page: https://github.com/OCA/purchase-reporting
License: AGPL-3
Author: Quartile Limited, Odoo Community Association (OCA)
Author-email: support@odoo-community.org
Classifier: Programming Language :: Python
Classifier: Framework :: Odoo
Classifier: Framework :: Odoo :: 18.0
Classifier: License :: OSI Approved :: GNU Affero General Public License v3
